dktemplate/__init__.py
dktemplate/apps.py
dktemplate/ast.py
dktemplate/find_template.py
dktemplate/parse.py
dktemplate/render.py
dktemplate/templatevars.py
dktemplate/tokenize.py
dktemplate/templatetags/__init__.py
dktemplate/templatetags/dktemplate_tags.py
dktemplate/templatetags/templateutils.py
dk_template-1.0.14.dist-info/LICENSE
dk_template-1.0.14.dist-info/METADATA
dk_template-1.0.14.dist-info/WHEEL
dk_template-1.0.14.dist-info/top_level.txt
dk_template-1.0.14.dist-info/RECORD
