Metadata-Version: 2.1
Name: dk-template
Version: 1.0.14
Summary: dk-template - debugging django templates.
Home-page: UNKNOWN
Author: Bjorn Pettersen
Author-email: bp@datakortet.no
License: UNKNOWN
Platform: UNKNOWN
Classifier: Development Status :: 5 - Production/Stable
Classifier: Intended Audience :: Developers
Classifier: Programming Language :: Python
Classifier: Programming Language :: Python :: 3
Classifier: Framework :: Django :: 1.11
Classifier: Framework :: Django :: 2.2
Classifier: Topic :: Software Development :: Libraries
License-File: LICENSE
Requires-Dist: django
Requires-Dist: dk
